README.md
setup.py
edflow/__init__.py
edflow/custom_logging.py
edflow/debug.py
edflow/edcache
edflow/edexplore
edflow/edflow
edflow/edlist
edflow/edsetup
edflow/explore.py
edflow/fpdb.py
edflow/main.py
edflow/project_manager.py
edflow/tf_util.py
edflow/util.py
edflow/applications/__init__.py
edflow/applications/tf_perceptual_loss.py
edflow/config/__init__.py
edflow/config/commandline_kwargs.py
edflow/data/__init__.py
edflow/data/dataset.py
edflow/data/dataset_mixin.py
edflow/data/agnostics/__init__.py
edflow/data/agnostics/concatenated.py
edflow/data/agnostics/csv_dset.py
edflow/data/agnostics/late_loading.py
edflow/data/agnostics/subdataset.py
edflow/data/believers/__init__.py
edflow/data/believers/meta.py
edflow/data/believers/meta_loaders.py
edflow/data/believers/meta_util.py
edflow/data/believers/meta_view.py
edflow/data/believers/sequence.py
edflow/data/processing/__init__.py
edflow/data/processing/labels.py
edflow/data/processing/processed.py
edflow/data/util/__init__.py
edflow/data/util/cached_dset.py
edflow/data/util/util_dsets.py
edflow/datasets/__init__.py
edflow/datasets/celeba.py
edflow/datasets/cifar.py
edflow/datasets/fashionmnist.py
edflow/datasets/mnist.py
edflow/datasets/utils.py
edflow/edsetup_files/__init__.py
edflow/edsetup_files/config.yaml
edflow/edsetup_files/dataset.py
edflow/edsetup_files/iterator.py
edflow/edsetup_files/model.py
edflow/eval/__init__.py
edflow/eval/pipeline.py
edflow/hooks/__init__.py
edflow/hooks/hook.py
edflow/hooks/pytorch_hooks.py
edflow/hooks/runtime_input.py
edflow/hooks/util_hooks.py
edflow/hooks/checkpoint_hooks/__init__.py
edflow/hooks/checkpoint_hooks/common.py
edflow/hooks/checkpoint_hooks/lambda_checkpoint_hook.py
edflow/hooks/checkpoint_hooks/tf_checkpoint_hook.py
edflow/hooks/checkpoint_hooks/torch_checkpoint_hook.py
edflow/hooks/logging_hooks/__init__.py
edflow/hooks/logging_hooks/minimal_logging_hook.py
edflow/hooks/logging_hooks/tf_logging_hook.py
edflow/hooks/metric_hooks/__init__.py
edflow_test.egg-info/PKG-INFO
edflow_test.egg-info/SOURCES.txt
edflow_test.egg-info/dependency_links.txt
edflow_test.egg-info/not-zip-safe
edflow_test.egg-info/requires.txt
edflow_test.egg-info/top_level.txt